mcp_server_dartou/__init__.py
mcp_server_dartou-0.2.1.dist-info/METADATA
mcp_server_dartou-0.2.1.dist-info/WHEEL
mcp_server_dartou-0.2.1.dist-info/entry_points.txt
mcp_server_dartou-0.2.1.dist-info/RECORD
